<Properties StartupConfiguration="{9AFDE709-8EE9-48CB-8B84-1E84130BB0B7}|Default">
  <MonoDevelop.Ide.Workspace ActiveConfiguration="Debug" />
  <MonoDevelop.Ide.Workbench ActiveDocument="04_Orders/Program.cs">
    <Files>
      <File FileName="04_Orders/Program.cs" Line="19" Column="55" />
    </Files>
    <Pads>
      <Pad Id="ProjectPad">
        <State name="__root__">
          <Node name="04_Orders" expanded="True">
            <Node name="04_Orders" expanded="True" />
          </Node>
        </State>
      </Pad>
      <Pad Id="MonoDevelop.Debugger.WatchPad">
        <State />
      </Pad>
    </Pads>
  </MonoDevelop.Ide.Workbench>
  <MultiItemStartupConfigurations />
  <MonoDevelop.Ide.DebuggingService.PinnedWatches />
  <MonoDevelop.Ide.ItemProperties.04__Orders PreferredExecutionTarget="MonoDevelop.Default" />
  <MonoDevelop.Ide.DebuggingService.Breakpoints>
    <BreakpointStore />
  </MonoDevelop.Ide.DebuggingService.Breakpoints>
</Properties>